trulens/otel/semconv/__init__.py
trulens/otel/semconv/constants.py
trulens/otel/semconv/trace.py
trulens_otel_semconv-2.5.3.dist-info/METADATA
trulens_otel_semconv-2.5.3.dist-info/WHEEL
trulens_otel_semconv-2.5.3.dist-info/RECORD
